Metadata-Version: 2.1
Name: imagebind-packaged
Version: 0.1.2
Summary: Updated version of Imagebind package with bug fixes.
Home-page: https://github.com/raghavdixit99/ImageBind
Author: Raghav Dixit
Classifier: Programming Language :: Python :: 3
Classifier: License :: OSI Approved :: MIT License
License-File: LICENSE
Requires-Dist: torch==1.13.0
Requires-Dist: torchvision==0.14.0
Requires-Dist: torchaudio==0.13.0
Requires-Dist: pytorchvideo==0.1.5
Requires-Dist: timm==0.6.7
Requires-Dist: ftfy
Requires-Dist: regex
Requires-Dist: einops
Requires-Dist: fvcore
Requires-Dist: eva-decord==0.6.1
Requires-Dist: iopath
Requires-Dist: numpy>=1.19
Requires-Dist: matplotlib
Requires-Dist: types-regex
Requires-Dist: mayavi
Requires-Dist: cartopy
